Metadata-Version: 1.1
Name: NYTimesArticleAPInew
Version: 1.0.0
Summary: Python wrapper for the New York Times Article Search API
Home-page: https://github.com/champebarton/NYTimesArticleAPI
Author: Champe Barton (@Mchampebartona)
Author-email: champebarton@gmail.com
License: MIT
Keywords: nytimes new york times api article search nyt journalism news
Platform: UNKNOWN
Classifier: Development Status :: 4 - Beta
Classifier: Intended Audience :: Developers
Classifier: License :: OSI Approved :: MIT License
Classifier: Operating System :: OS Independent
Classifier: Programming Language :: Python :: 2
Classifier: Programming Language :: Python :: 2.7
Classifier: Programming Language :: Python :: 3
Classifier: Programming Language :: Python :: 3.2
Classifier: Programming Language :: Python :: 3.3
Classifier: Programming Language :: Python :: 3.4
Classifier: Programming Language :: Python :: 3.5
Classifier: Programming Language :: Python :: 3.6
Classifier: Topic :: Internet :: WWW/HTTP :: Dynamic Content :: News/Diary
Classifier: Topic :: Office/Business :: News/Diary
Classifier: Topic :: Software Development :: Libraries :: Python Modules
